{
  "project_info": {
    "project_number": "37424093970",
    "project_id": "sihaty-app",
    "storage_bucket": "sihaty-app.appspot.com"
  },
  "client": [
    {
      "client_info": {
        "mobilesdk_app_id": "1:37424093970:android:999de98919792bb58fb1cb",
        "android_client_info": {
          "package_name": "com.example.sihaty_app"
        }
      },
      "oauth_client": [],
      "api_key": [
        {
          "current_key": "AIzaSyA1LALK4jlxX7JQmjYtR8f3f2RxUKQTclg"
        }
      ],
      "services": {
        "appinvite_service": {
          "other_platform_oauth_client": []
        }
      }
    }
  ],
  "configuration_version": "1"
}